geeft.py
geeft-0.1.2.dist-info/LICENSE
geeft-0.1.2.dist-info/METADATA
geeft-0.1.2.dist-info/WHEEL
geeft-0.1.2.dist-info/top_level.txt
geeft-0.1.2.dist-info/RECORD
